{
    "exp_name": "train",
    "seed": 42,
    "torch_deterministic": true,
    "cuda": true,
    "track": false,
    "wandb_project_name": "cleanRL",
    "wandb_entity": null,
    "capture_video": false,
    "env_id": "LuxAI_S2-v0",
    "total_timesteps": 100000000,
    "learning_rate": 0.0001,
    "num_envs": 16,
    "num_steps": 1024,
    "anneal_lr": true,
    "gamma": 0.99,
    "gae_lambda": 0.95,
    "train_num_collect": 2048,
    "num_minibatches": 16,
    "update_epochs": 4,
    "norm_adv": true,
    "clip_coef": 0.2,
    "clip_vloss": true,
    "ent_coef": 0.01,
    "vf_coef": 0.5,
    "max_grad_norm": 0.5,
    "target_kl": null,
    "num_worker": 1,
    "save_interval": 100000,
    "load_model_path": null,
    "evaluate_interval": 10000,
    "evaluate_num": 5,
    "eval": false,
    "batch_size": 16384,
    "minibatch_size": 128,
    "max_train_step": 128
}